Metadata-Version: 1.0
Name: Flask-WhooshAlchemy
Version: 0.4a
Summary: Whoosh extension to Flask/SQLAlchemy
Home-page: https://github.com/gyllstromk/Flask-WhooshAlchemy
Author: Karl Gyllstrom
Author-email: karl.gyllstrom+code@gmail.com
License: BSD
Platform: any
